corso/__init__.py
corso/az.py
corso/cli.py
corso/evaluation.py
corso/minmax.py
corso/model.py
corso/pg.py
corso/utils.py
corso-1.1.0.dist-info/LICENSE
corso-1.1.0.dist-info/METADATA
corso-1.1.0.dist-info/WHEEL
corso-1.1.0.dist-info/top_level.txt
corso-1.1.0.dist-info/RECORD
