Metadata-Version: 2.1
Name: corso
Version: 1.1.0
Summary: Environment for the game of Corso + AI tools.
Home-page: http://github.com/Ball-Man/corso
Author: Francesco Mistri
Author-email: franc.mistri@gmail.com
License: MIT
Classifier: Intended Audience :: Developers
Classifier: Programming Language :: Python :: 3 :: Only
Classifier: Topic :: Games/Entertainment
Requires-Python: >=3.9
License-File: LICENSE
Provides-Extra: all
Requires-Dist: numpy ; extra == 'all'
Requires-Dist: torch ; extra == 'all'
Requires-Dist: tensorboard ; extra == 'all'
Requires-Dist: packaging ; extra == 'all'
Provides-Extra: az
Requires-Dist: numpy ; extra == 'az'
Requires-Dist: torch ; extra == 'az'
Requires-Dist: tensorboard ; extra == 'az'
Requires-Dist: packaging ; extra == 'az'
Provides-Extra: pg
Requires-Dist: numpy ; extra == 'pg'
Requires-Dist: torch ; extra == 'pg'
Requires-Dist: tensorboard ; extra == 'pg'
Requires-Dist: packaging ; extra == 'pg'
